{"nodes":[{"label":"GhostEzra","x":-244.44500732421875,"y":-185.22943115234375,"id":"18","attributes":{"country":"US","notes":"One of the biggest US Qanon influencers, very antisemitic; identity: https://www.logically.ai/articles/exclusive-ghostezra-florida-man-largest-antisemitic-forum","public":"true","chat":"false","platform_id":"1435468415","source":"researcher","category":"conspiracy","screenname":"GhostEzra","platform":"Telegram","url":"https://t.me/GhostEzra"},"color":"rgb(210,124,206)","size":19.125},{"label":"Danïelle Chat","x":194.17356872558594,"y":138.544921875,"id":"47","attributes":{"platform_id":"1403713875","source":"TelegramTelethonTransformer 0.0.1","category":"forwarded","screenname":"DanielleStotijn","platform":"Telegram","url":"https://t.me/s/DanielleStotijn"},"color":"rgb(0,0,0)","size":1.0},{"label":"De Gulden Middenweg","x":409.1643981933594,"y":64.06991577148438,"id":"32","attributes":{"platform_id":"1187741976","source":"TelegramTelethonTransformer 0.0.1","category":"forwarded","screenname":"deguldenmiddenweg","platform":"Telegram","url":"https://t.me/s/deguldenmiddenweg"},"color":"rgb(0,0,0)","size":10.0625},{"label":"Truthsocial.com","x":108.17720794677734,"y":-159.3551483154297,"id":"41","attributes":{"platform_id":"1798187566","source":"TelegramTelethonTransformer 0.0.1","category":"forwarded","screenname":"TRUTHSocial_TMTG","platform":"Telegram","url":"https://t.me/s/TRUTHSocial_TMTG"},"color":"rgb(0,0,0)","size":13.6875},{"x":323.16802978515625,"y":64.06991577148438,"id":"54","attributes":{},"color":"rgb(0,0,0)","size":1.0},{"x":194.17356872558594,"y":-159.3551483154297,"id":"53","attributes":{"notes":"ChannelPrivateError","platform_id":"1438350073","source":"TelegramTelethonTransformer 0.0.1","category":"forwarded","platform":"Telegram","url":"https://t.me/s/"},"color":"rgb(0,0,0)","size":1.0},{"label":"Tim Gielen","x":65.17904663085938,"y":-84.88011932373047,"id":"33","attributes":{"platform_id":"1451097674","source":"TelegramTelethonTransformer 0.0.1","category":"forwarded","screenname":"timgielen","platform":"Telegram","url":"https://t.me/s/timgielen"},"color":"rgb(0,0,0)","size":2.8125},{"label":"Q) The Storm Rider /Official Page","x":108.17720794677734,"y":138.544921875,"id":"29","attributes":{"platform_id":"1459255169","source":"TelegramTelethonTransformer 0.0.1","category":"forwarded","screenname":"qthestormrider777","platform":"Telegram","url":"https://t.me/s/qthestormrider777"},"color":"rgb(0,0,0)","size":24.5625},{"label":"Nederlands Verzet Kanaal","x":280.16986083984375,"y":-10.405104637145996,"id":"31","attributes":{"platform_id":"1231902969","source":"TelegramTelethonTransformer 0.0.1","category":"forwarded","platform":"Telegram"},"color":"rgb(0,0,0)","size":10.0625},{"label":"WhipLash347","x":-63.815460205078125,"y":-159.3551483154297,"id":"25","attributes":{"platform_id":"1168034208","source":"TelegramTelethonTransformer 0.0.1","category":"forwarded","screenname":"Whiplash347","platform":"Telegram","url":"https://t.me/s/Whiplash347"},"color":"rgb(0,0,0)","size":19.125},{"label":"Ezra A. Cohen","x":22.18088150024414,"y":-159.3551483154297,"id":"26","attributes":{"platform_id":"1255633610","source":"TelegramTelethonTransformer 0.0.1","category":"forwarded","screenname":"EzraACohen","platform":"Telegram","url":"https://t.me/s/EzraACohen"},"color":"rgb(0,0,0)","size":19.125},{"label":"@realJohnQuent","x":-20.81728744506836,"y":-84.88011932373047,"id":"34","attributes":{"platform_id":"1329029113","source":"TelegramTelethonTransformer 0.0.1","category":"forwarded","screenname":"realJohnQuent","platform":"Telegram","url":"https://t.me/s/realJohnQuent"},"color":"rgb(0,0,0)","size":15.5},{"label":"American Patriot","x":-287.4431457519531,"y":-259.7044372558594,"id":"7","attributes":{"country":"US","public":"true","chat":"false","platform_id":"1362890584","source":"researcher","category":"explicit_qanon","screenname":"ishjay1960","platform":"Telegram","url":"https://t.me/s/ishjay1960"},"color":"rgb(210,124,206)","size":11.875},{"label":"The Real Kim Shady™️👽","x":65.17904663085938,"y":64.06991577148438,"id":"28","attributes":{"platform_id":"1152339833","source":"TelegramTelethonTransformer 0.0.1","category":"forwarded","screenname":"TheRealKimShady","platform":"Telegram","url":"https://t.me/s/TheRealKimShady"},"color":"rgb(0,0,0)","size":17.3125},{"label":"Wakker worden met Aart","x":237.17172241210938,"y":-84.88011932373047,"id":"37","attributes":{"platform_id":"1358275156","source":"TelegramTelethonTransformer 0.0.1","category":"forwarded","screenname":"wakker_worden_met_aart","platform":"Telegram","url":"https://t.me/s/wakker_worden_met_aart"},"color":"rgb(0,0,0)","size":2.8125},{"label":"TRUTHREVEALEDCHANNEL","x":-244.44500732421875,"y":-334.179443359375,"id":"1","attributes":{"country":"US","public":"true","chat":"false","platform_id":"1275697756","source":"researcher","category":"conspiracy","screenname":"TRUTHREVEALEDCHANNEL","platform":"Telegram","url":"https://ttttt.me/TRUTHREVEALEDCHANNEL"},"color":"rgb(210,124,206)","size":4.625},{"label":"The Neighbours","x":280.16986083984375,"y":138.544921875,"id":"38","attributes":{"platform_id":"1271635049","source":"TelegramTelethonTransformer 0.0.1","category":"forwarded","screenname":"theneighbours2021","platform":"Telegram","url":"https://t.me/s/theneighbours2021"},"color":"rgb(0,0,0)","size":2.8125},{"label":"fuf media - freiheit denken","x":-289.3408203125,"y":-10.405104637145996,"id":"13","attributes":{"country":"DE","notes":"The channel says \"Inklusive aufbereitete News der Anons aus den USA plus weitere interessante Infos aus diversen Social Media Plattformen\n\" It\u0027s difficult to put it in the right category, it could also be a qanon_content channel","public":"true","chat":"false","platform_id":"1337894333","source":"researcher","category":"explicit_qanon","screenname":"fufmedia","platform":"Telegram","url":"https://t.me/s/fufmedia"},"color":"rgb(255,116,62)","size":6.4375},{"label":"Lincy-Verona Stubbe 🦄🦋🙏🏼","x":65.17904663085938,"y":-233.8301544189453,"id":"51","attributes":{"platform_id":"1643833206","source":"TelegramTelethonTransformer 0.0.1","category":"forwarded","screenname":"ascencion5dcollective","platform":"Telegram","url":"https://t.me/s/ascencion5dcollective"},"color":"rgb(0,0,0)","size":1.0},{"label":"Truth Social Live","x":151.17539978027344,"y":213.0199432373047,"id":"52","attributes":{"platform_id":"1709824862","source":"TelegramTelethonTransformer 0.0.1","category":"forwarded","screenname":"truthsocialapplive","platform":"Telegram","url":"https://t.me/s/truthsocialapplive"},"color":"rgb(0,0,0)","size":1.0},{"label":"Daniëlle Stotijn","x":-117.86283874511719,"y":30.68096923828125,"id":"16","attributes":{"country":"NL","influencer":"Danielle Stotijn","public":"true","chat":"false","platform_id":"1239878493","source":"researcher","category":"qanon","screenname":"DDay1978","platform":"Telegram","url":"https://t.me/DDay1978"},"color":"rgb(104,173,54)","size":30.0},{"label":"Q World Order","x":-201.4468231201172,"y":-259.7044372558594,"id":"14","attributes":{"country":"US","public":"true","chat":"false","platform_id":"1429321216","source":"researcher","category":"explicit_qanon","screenname":"QWO17","platform":"Telegram","url":"https://t.me/s/QWO17"},"color":"rgb(210,124,206)","size":13.6875},{"label":"True Self True World - Alexander Rice","x":366.16619873046875,"y":138.544921875,"id":"50","attributes":{"platform_id":"1207264774","source":"TelegramTelethonTransformer 0.0.1","category":"forwarded","screenname":"trueselftrueworld","platform":"Telegram","url":"https://t.me/s/trueselftrueworld"},"color":"rgb(0,0,0)","size":1.0},{"label":"The DEFCON Warning System","x":151.17539978027344,"y":-233.8301544189453,"id":"27","attributes":{"platform_id":"1338045376","source":"TelegramTelethonTransformer 0.0.1","category":"forwarded","screenname":"DEFCONWarningSystem","platform":"Telegram","url":"https://t.me/s/DEFCONWarningSystem"},"color":"rgb(0,0,0)","size":1.0},{"label":"AVV vaccinatieschade meldpunt","x":-240.40908813476562,"y":302.2862243652344,"id":"2","attributes":{"country":"NL","notes":"Meldpunt van bijwerkingen na vaccinatie of booster; Artsen voor vrijheid","influencer":"AVV vaccinatieschade","public":"true","chat":"true","platform_id":"1445727482","source":"researcher","category":"corona/anti-vax","screenname":"AVVvaccinatieschademelden","platform":"Telegram","url":"https://t.me/AVVvaccinatieschademelden"},"color":"rgb(104,173,54)","size":2.8125},{"label":"D.U.M.B.S. and Underground War","x":-330.44134521484375,"y":-185.22943115234375,"id":"6","attributes":{"country":"US","public":"true","chat":"false","platform_id":"1583188112","source":"researcher","category":"conspiracy","screenname":"DUMBSandUnderground","platform":"Telegram","url":"https://t.me/s/DUMBSandUnderground"},"color":"rgb(210,124,206)","size":13.6875},{"label":"Pepe Lives Matter","x":-158.4486541748047,"y":-185.22943115234375,"id":"12","attributes":{"country":"US","notes":"Extreem rechte, antisemitische berichten","influencer":"Pepe Lives Matter","public":"true","chat":"false","platform_id":"1390659157","source":"researcher","category":"explicit_qanon","screenname":"PepeMatter","platform":"Telegram","url":"https://t.me/PepeMatter"},"color":"rgb(210,124,206)","size":24.5625},{"label":"GESARA NEDERLAND (kanaal)","x":-111.41456604003906,"y":227.81121826171875,"id":"5","attributes":{"country":"NL","public":"true","chat":"false","platform_id":"1471525292","source":"researcher","category":"qanon_content","screenname":"GesaraNederland","platform":"Telegram","url":"https://t.me/GesaraNederland"},"color":"rgb(104,173,54)","size":6.4375},{"label":"Lions News","x":323.16802978515625,"y":-84.88011932373047,"id":"43","attributes":{"platform_id":"1507167857","source":"TelegramTelethonTransformer 0.0.1","category":"forwarded","screenname":"LionsNews","platform":"Telegram","url":"https://t.me/s/LionsNews"},"color":"rgb(0,0,0)","size":6.4375},{"label":"Disclose.tv","x":237.17172241210938,"y":64.06991577148438,"id":"20","attributes":{"platform_id":"1179270258","source":"TelegramTelethonTransformer 0.0.1","category":"forwarded","screenname":"disclosetv","platform":"Telegram","url":"https://t.me/s/disclosetv"},"color":"rgb(0,0,0)","size":30.0},{"label":"Schumann Resonance Report","x":237.17172241210938,"y":213.0199432373047,"id":"39","attributes":{"platform_id":"1466820863","source":"TelegramTelethonTransformer 0.0.1","category":"forwarded","screenname":"SchumannResonanceReport","platform":"Telegram","url":"https://t.me/s/SchumannResonanceReport"},"color":"rgb(0,0,0)","size":2.8125},{"label":"Historie","x":366.16619873046875,"y":-159.3551483154297,"id":"40","attributes":{"platform_id":"1418688957","source":"TelegramTelethonTransformer 0.0.1","category":"forwarded","screenname":"WahreHistorie","platform":"Telegram","url":"https://t.me/s/WahreHistorie"},"color":"rgb(0,0,0)","size":1.0},{"label":"Stew Peters 📢🇺🇸","x":-63.815460205078125,"y":138.544921875,"id":"22","attributes":{"platform_id":"1494502630","source":"TelegramTelethonTransformer 0.0.1","category":"forwarded","screenname":"stewpeters","platform":"Telegram","url":"https://t.me/s/stewpeters"},"color":"rgb(0,0,0)","size":15.5},{"label":"AVV vaccinatieschade","x":-154.41275024414062,"y":302.2862243652344,"id":"10","attributes":{"country":"NL","notes":"Meldpunt van bijwerkingen na vaccinatie of booster; Artsen voor vrijheid","influencer":"AVV vaccinatieschade","public":"true","chat":"false","platform_id":"1552743745","source":"researcher","category":"corona/anti-vax","screenname":"AVVvaccinatieschade","platform":"Telegram","url":"https://t.me/AVVvaccinatieschade"},"color":"rgb(104,173,54)","size":6.4375},{"label":"Ella Ster","x":-283.40728759765625,"y":227.81121826171875,"id":"17","attributes":{"country":"NL","notes":"Blogster over satanistisch kindermisbruik","influencer":"Ella Ster","public":"true","chat":"false","platform_id":"1246068475","source":"researcher","category":"qanon_content","screenname":"ella_ster","platform":"Telegram","url":"https://t.me/ella_ster"},"color":"rgb(104,173,54)","size":6.4375},{"label":"MistyG ⭐️⭐️⭐️","x":22.18088150024414,"y":138.544921875,"id":"23","attributes":{"platform_id":"1481320011","source":"TelegramTelethonTransformer 0.0.1","category":"forwarded","screenname":"MistyG17","platform":"Telegram","url":"https://t.me/s/MistyG17"},"color":"rgb(0,0,0)","size":15.5},{"label":"Dear Danny...","x":-106.81362915039062,"y":-84.88011932373047,"id":"42","attributes":{"platform_id":"1437981826","source":"TelegramTelethonTransformer 0.0.1","category":"forwarded","screenname":"deardanny","platform":"Telegram","url":"https://t.me/s/deardanny"},"color":"rgb(0,0,0)","size":1.0},{"label":"ConservativeJblQck1776","x":366.16619873046875,"y":-10.405104637145996,"id":"44","attributes":{"platform_id":"1656992334","source":"TelegramTelethonTransformer 0.0.1","category":"forwarded","screenname":"conservativejblQck1776","platform":"Telegram","url":"https://t.me/s/conservativejblQck1776"},"color":"rgb(0,0,0)","size":2.8125},{"label":"Nicholas Veniamin","x":-330.44134521484375,"y":-334.179443359375,"id":"15","attributes":{"country":"US","influencer":"Nicholas Veniamin","public":"true","chat":"false","platform_id":"1384836446","source":"researcher","category":"conspiracy","screenname":"NicholasVeniamin","platform":"Telegram","url":"https://t.me/NicholasVeniamin"},"color":"rgb(210,124,206)","size":13.6875},{"label":"Russian MFA 🇷🇺","x":108.17720794677734,"y":-10.405104637145996,"id":"30","attributes":{"platform_id":"1074511071","source":"TelegramTelethonTransformer 0.0.1","category":"forwarded","screenname":"MFARussia","platform":"Telegram","url":"https://t.me/s/MFARussia"},"color":"rgb(0,0,0)","size":8.25},{"label":"Patrick Bouvier Kennedy","x":151.17539978027344,"y":-84.88011932373047,"id":"35","attributes":{"platform_id":"1465550494","source":"TelegramTelethonTransformer 0.0.1","category":"forwarded","screenname":"PatrickKennedy777","platform":"Telegram","url":"https://t.me/s/PatrickKennedy777"},"color":"rgb(0,0,0)","size":8.25},{"label":"GreatBritishBird News","x":-184.7405548095703,"y":102.92967987060547,"id":"8","attributes":{"country":"GB","notes":"UK focused conspiracy news","public":"true","chat":"false","platform_id":"1232861332","source":"researcher","category":"conspiracy","screenname":"GreatBritishBird_News","platform":"Telegram","url":"https://t.me/GreatBritishBird_News"},"color":"rgb(0,183,218)","size":8.25},{"label":"Artsen voor Vrijheid","x":-197.41090393066406,"y":376.76129150390625,"id":"11","attributes":{"country":"NL","notes":"Artsen? die berichten posten over vaccinaties","influencer":"Artsen voor Vrijheid","public":"true","chat":"false","platform_id":"1399429727","source":"researcher","category":"corona/anti-vax","screenname":"artsenvoorvrijheid","platform":"Telegram","url":"https://t.me/artsenvoorvrijheid"},"color":"rgb(104,173,54)","size":4.625},{"label":"SpecialQForces","x":-91.81645202636719,"y":-364.27337646484375,"id":"0","attributes":{"country":"US","public":"true","chat":"false","platform_id":"1576562559","source":"researcher","category":"explicit_qanon","screenname":"SpecialQForces","platform":"Telegram","url":"https://ttttt.me/SpecialQForces"},"color":"rgb(210,124,206)","size":17.3125},{"label":"DUTCH DIGGER NEWS","x":-197.41090393066406,"y":227.81121826171875,"id":"3","attributes":{"country":"NL","notes":"Meeste berichten zijn over corona/vaccins/booster/maatregelen, maar ze delen ook Qanon sympathien zoals Nuremberg etc","influencer":"THE DUTCH PATRIOT","public":"true","chat":"false","platform_id":"1210971815","source":"researcher","category":"qanon_content","screenname":"maddogholland","platform":"Telegram","url":"https://t.me/maddogholland"},"color":"rgb(104,173,54)","size":15.5},{"label":"Rinus Verhagen","x":-283.40728759765625,"y":376.76129150390625,"id":"4","attributes":{"country":"NL","notes":"Qanon, Gesara, Great reset en crypto Baafse munt","influencer":"Rinus Verhagen","public":"true","chat":"false","platform_id":"1644190850","source":"researcher","category":"qanon_content","screenname":"RinusVerhagen","platform":"Telegram","url":"https://t.me/RinusVerhagen"},"color":"rgb(104,173,54)","size":6.4375},{"label":"Jim Corr News","x":-20.81728744506836,"y":64.06991577148438,"id":"45","attributes":{"platform_id":"1226106091","source":"TelegramTelethonTransformer 0.0.1","category":"forwarded","screenname":"jimcorr","platform":"Telegram","url":"https://t.me/s/jimcorr"},"color":"rgb(0,0,0)","size":2.8125},{"label":"The Paranormies Present","x":-63.815460205078125,"y":-10.405104637145996,"id":"24","attributes":{"platform_id":"1452921969","source":"TelegramTelethonTransformer 0.0.1","category":"forwarded","screenname":"TheParanormiesPresent","platform":"Telegram","url":"https://t.me/s/TheParanormiesPresent"},"color":"rgb(0,0,0)","size":1.0},{"label":"Inessa S","x":65.17904663085938,"y":213.0199432373047,"id":"48","attributes":{"platform_id":"1795183969","source":"TelegramTelethonTransformer 0.0.1","category":"forwarded","screenname":"inessas100","platform":"Telegram","url":"https://t.me/s/inessas100"},"color":"rgb(0,0,0)","size":6.4375},{"label":"MH17 Truth","x":151.17539978027344,"y":64.06991577148438,"id":"49","attributes":{"platform_id":"1518295587","source":"TelegramTelethonTransformer 0.0.1","category":"forwarded","screenname":"MH17thruth","platform":"Telegram","url":"https://t.me/s/MH17thruth"},"color":"rgb(0,0,0)","size":1.0},{"label":"SHELLSHQCK 🧨💥🇺🇸","x":-373.4394836425781,"y":-259.7044372558594,"id":"19","attributes":{"country":"US","public":"true","chat":"false","platform_id":"1293946304","source":"researcher","category":"explicit_qanon","screenname":"ShellShQck","platform":"Telegram","url":"https://t.me/ShellShQck"},"color":"rgb(210,124,206)","size":8.25},{"label":"Insider Paper","x":22.18088150024414,"y":-10.405104637145996,"id":"21","attributes":{"platform_id":"1452037375","source":"TelegramTelethonTransformer 0.0.1","category":"forwarded","screenname":"insiderpaper","platform":"Telegram","url":"https://t.me/s/insiderpaper"},"color":"rgb(0,0,0)","size":17.3125},{"label":"AGENDA 21⛔️Channel","x":280.16986083984375,"y":-159.3551483154297,"id":"36","attributes":{"platform_id":"1277477770","source":"TelegramTelethonTransformer 0.0.1","category":"forwarded","screenname":"kvsnwo","platform":"Telegram","url":"https://t.me/s/kvsnwo"},"color":"rgb(0,0,0)","size":11.875},{"label":"Expose the PEDOS END the CABAL","x":-203.3444366455078,"y":-10.405104637145996,"id":"9","attributes":{"country":"DE","notes":"Channel shares mostly english-language content but a few German-language posts suggest some kind of connection to Germany","public":"true","chat":"false","platform_id":"1508710229","source":"researcher","category":"qanon_content","screenname":"ExposeThePEDOSendTheCABAL","platform":"Telegram","url":"https://t.me/ExposeThePEDOSendTheCABAL"},"color":"rgb(255,116,62)","size":13.6875},{"label":"Kushy’s News🐸","x":194.17356872558594,"y":-10.405104637145996,"id":"46","attributes":{"platform_id":"1416638314","source":"TelegramTelethonTransformer 0.0.1","category":"forwarded","screenname":"kushsyndicate1776","platform":"Telegram","url":"https://t.me/s/kushsyndicate1776"},"color":"rgb(0,0,0)","size":1.0}],"edges":[{"source":"0","target":"6","id":"4326","attributes":{},"color":"rgb(210,124,206)","size":6210.0},{"source":"9","target":"0","id":"4409","attributes":{},"color":"rgb(232,120,134)","size":3444.0},{"source":"9","target":"4","id":"4413","attributes":{},"color":"rgb(179,144,58)","size":10.0},{"source":"20","target":"13","id":"4465","attributes":{},"color":"rgb(127,58,31)","size":15.0},{"source":"22","target":"14","id":"4491","attributes":{},"color":"rgb(105,62,103)","size":2.0},{"source":"3","target":"3","id":"4342","attributes":{},"color":"rgb(104,173,54)","size":168.0},{"source":"12","target":"13","id":"4354","attributes":{},"color":"rgb(232,120,134)","size":44.0},{"source":"48","target":"1","id":"4617","attributes":{},"color":"rgb(105,62,103)","size":1.0},{"source":"12","target":"1","id":"4349","attributes":{},"color":"rgb(210,124,206)","size":82.0},{"source":"26","target":"14","id":"4522","attributes":{},"color":"rgb(105,62,103)","size":92.0},{"source":"4","target":"3","id":"4370","attributes":{},"color":"rgb(104,173,54)","size":11.0},{"source":"8","target":"9","id":"4408","attributes":{},"color":"rgb(127,149,140)","size":1.0},{"source":"30","target":"1","id":"4552","attributes":{},"color":"rgb(105,62,103)","size":1.0},{"source":"20","target":"18","id":"4471","attributes":{},"color":"rgb(105,62,103)","size":5.0},{"source":"18","target":"0","id":"4417","attributes":{},"color":"rgb(210,124,206)","size":10.0},{"source":"2","target":"10","id":"4334","attributes":{},"color":"rgb(104,173,54)","size":12.0},{"source":"16","target":"16","id":"4457","attributes":{},"color":"rgb(104,173,54)","size":204.0},{"source":"3","target":"11","id":"4343","attributes":{},"color":"rgb(104,173,54)","size":139.0},{"source":"47","target":"16","id":"4616","attributes":{},"color":"rgb(52,86,27)","size":2.0},{"source":"29","target":"0","id":"4537","attributes":{},"color":"rgb(105,62,103)","size":172.0},{"source":"21","target":"13","id":"4480","attributes":{},"color":"rgb(127,58,31)","size":9.0},{"source":"35","target":"9","id":"4582","attributes":{},"color":"rgb(127,58,31)","size":1.0},{"source":"29","target":"9","id":"4548","attributes":{},"color":"rgb(127,58,31)","size":68.0},{"source":"12","target":"6","id":"4355","attributes":{},"color":"rgb(210,124,206)","size":3.0},{"source":"34","target":"16","id":"4578","attributes":{},"color":"rgb(52,86,27)","size":1.0},{"source":"15","target":"3","id":"4430","attributes":{},"color":"rgb(157,148,130)","size":2.0},{"source":"19","target":"9","id":"4439","attributes":{},"color":"rgb(232,120,134)","size":5.0},{"source":"25","target":"3","id":"4506","attributes":{},"color":"rgb(52,86,27)","size":41.0},{"source":"21","target":"0","id":"4475","attributes":{},"color":"rgb(105,62,103)","size":1.0},{"source":"3","target":"4","id":"4344","attributes":{},"color":"rgb(104,173,54)","size":187.0},{"source":"20","target":"8","id":"4469","attributes":{},"color":"rgb(0,91,109)","size":6.0},{"source":"21","target":"4","id":"4479","attributes":{},"color":"rgb(52,86,27)","size":1.0},{"source":"21","target":"14","id":"4482","attributes":{},"color":"rgb(105,62,103)","size":648.0},{"source":"0","target":"5","id":"4325","attributes":{},"color":"rgb(157,148,130)","size":6.0},{"source":"16","target":"19","id":"4456","attributes":{},"color":"rgb(157,148,130)","size":1.0},{"source":"28","target":"3","id":"4529","attributes":{},"color":"rgb(52,86,27)","size":25.0},{"source":"10","target":"11","id":"4337","attributes":{},"color":"rgb(104,173,54)","size":28.0},{"source":"22","target":"0","id":"4485","attributes":{},"color":"rgb(105,62,103)","size":6.0},{"source":"25","target":"6","id":"4508","attributes":{},"color":"rgb(105,62,103)","size":2.0},{"source":"7","target":"3","id":"4391","attributes":{},"color":"rgb(157,148,130)","size":20.0},{"source":"24","target":"16","id":"4503","attributes":{},"color":"rgb(52,86,27)","size":1.0},{"source":"36","target":"9","id":"4589","attributes":{},"color":"rgb(127,58,31)","size":1.0},{"source":"32","target":"11","id":"4564","attributes":{},"color":"rgb(52,86,27)","size":1.0},{"source":"21","target":"1","id":"4476","attributes":{},"color":"rgb(105,62,103)","size":51.0},{"source":"6","target":"5","id":"4385","attributes":{},"color":"rgb(157,148,130)","size":35.0},{"source":"20","target":"4","id":"4464","attributes":{},"color":"rgb(52,86,27)","size":4.0},{"source":"12","target":"16","id":"4361","attributes":{},"color":"rgb(157,148,130)","size":5.0},{"source":"5","target":"5","id":"4376","attributes":{},"color":"rgb(104,173,54)","size":43.0},{"source":"13","target":"9","id":"4380","attributes":{},"color":"rgb(255,116,62)","size":2.0},{"source":"3","target":"7","id":"4346","attributes":{},"color":"rgb(157,148,130)","size":1.0},{"source":"29","target":"7","id":"4546","attributes":{},"color":"rgb(105,62,103)","size":54.0},{"source":"26","target":"16","id":"4525","attributes":{},"color":"rgb(52,86,27)","size":8.0},{"source":"17","target":"5","id":"4367","attributes":{},"color":"rgb(104,173,54)","size":1.0},{"source":"20","target":"0","id":"4458","attributes":{},"color":"rgb(105,62,103)","size":2.0},{"source":"19","target":"0","id":"4436","attributes":{},"color":"rgb(210,124,206)","size":14.0},{"source":"23","target":"12","id":"4497","attributes":{},"color":"rgb(105,62,103)","size":22.0},{"source":"29","target":"19","id":"4549","attributes":{},"color":"rgb(105,62,103)","size":14.0},{"source":"29","target":"11","id":"4541","attributes":{},"color":"rgb(52,86,27)","size":1.0},{"source":"25","target":"4","id":"4507","attributes":{},"color":"rgb(52,86,27)","size":30.0},{"source":"7","target":"5","id":"4393","attributes":{},"color":"rgb(157,148,130)","size":1.0},{"source":"3","target":"9","id":"4347","attributes":{},"color":"rgb(179,144,58)","size":1.0},{"source":"39","target":"16","id":"4596","attributes":{},"color":"rgb(52,86,27)","size":3.0},{"source":"6","target":"2","id":"4383","attributes":{},"color":"rgb(157,148,130)","size":1.0},{"source":"29","target":"4","id":"4542","attributes":{},"color":"rgb(52,86,27)","size":4.0},{"source":"36","target":"4","id":"4587","attributes":{},"color":"rgb(52,86,27)","size":2.0},{"source":"1","target":"2","id":"4331","attributes":{},"color":"rgb(157,148,130)","size":1.0},{"source":"36","target":"11","id":"4586","attributes":{},"color":"rgb(52,86,27)","size":1.0},{"source":"12","target":"7","id":"4356","attributes":{},"color":"rgb(210,124,206)","size":29.0},{"source":"15","target":"2","id":"4429","attributes":{},"color":"rgb(157,148,130)","size":2.0},{"source":"4","target":"4","id":"4371","attributes":{},"color":"rgb(104,173,54)","size":10.0},{"source":"25","target":"14","id":"4510","attributes":{},"color":"rgb(105,62,103)","size":25.0},{"source":"35","target":"16","id":"4583","attributes":{},"color":"rgb(52,86,27)","size":1.0},{"source":"14","target":"7","id":"4402","attributes":{},"color":"rgb(210,124,206)","size":30.0},{"source":"9","target":"1","id":"4410","attributes":{},"color":"rgb(232,120,134)","size":13.0},{"source":"21","target":"8","id":"4483","attributes":{},"color":"rgb(0,91,109)","size":9.0},{"source":"9","target":"9","id":"4416","attributes":{},"color":"rgb(255,116,62)","size":1985.0},{"source":"18","target":"12","id":"4420","attributes":{},"color":"rgb(210,124,206)","size":1.0},{"source":"7","target":"0","id":"4389","attributes":{},"color":"rgb(210,124,206)","size":2.0},{"source":"30","target":"0","id":"4551","attributes":{},"color":"rgb(105,62,103)","size":1.0},{"source":"16","target":"6","id":"4450","attributes":{},"color":"rgb(157,148,130)","size":12.0},{"source":"36","target":"1","id":"4584","attributes":{},"color":"rgb(105,62,103)","size":2.0},{"source":"22","target":"3","id":"4488","attributes":{},"color":"rgb(52,86,27)","size":1.0},{"source":"6","target":"7","id":"4387","attributes":{},"color":"rgb(210,124,206)","size":22.0},{"source":"20","target":"1","id":"4459","attributes":{},"color":"rgb(105,62,103)","size":119.0},{"source":"20","target":"7","id":"4467","attributes":{},"color":"rgb(105,62,103)","size":66.0},{"source":"16","target":"15","id":"4455","attributes":{},"color":"rgb(157,148,130)","size":1.0},{"source":"50","target":"16","id":"4622","attributes":{},"color":"rgb(52,86,27)","size":9.0},{"source":"34","target":"14","id":"4575","attributes":{},"color":"rgb(105,62,103)","size":1.0},{"source":"31","target":"4","id":"4559","attributes":{},"color":"rgb(52,86,27)","size":66.0},{"source":"30","target":"16","id":"4555","attributes":{},"color":"rgb(52,86,27)","size":2.0},{"source":"28","target":"16","id":"4536","attributes":{},"color":"rgb(52,86,27)","size":1.0},{"source":"25","target":"16","id":"4514","attributes":{},"color":"rgb(52,86,27)","size":15.0},{"source":"0","target":"2","id":"4322","attributes":{},"color":"rgb(157,148,130)","size":1.0},{"source":"25","target":"18","id":"4512","attributes":{},"color":"rgb(105,62,103)","size":1.0},{"source":"6","target":"6","id":"4386","attributes":{},"color":"rgb(210,124,206)","size":3819.0},{"source":"21","target":"16","id":"4484","attributes":{},"color":"rgb(52,86,27)","size":1.0},{"source":"20","target":"11","id":"4463","attributes":{},"color":"rgb(52,86,27)","size":1.0},{"source":"16","target":"3","id":"4445","attributes":{},"color":"rgb(104,173,54)","size":2.0},{"source":"15","target":"1","id":"4428","attributes":{},"color":"rgb(210,124,206)","size":2.0},{"source":"16","target":"10","id":"4444","attributes":{},"color":"rgb(104,173,54)","size":1.0},{"source":"16","target":"8","id":"4453","attributes":{},"color":"rgb(52,178,136)","size":3.0},{"source":"13","target":"0","id":"4377","attributes":{},"color":"rgb(232,120,134)","size":1.0},{"source":"43","target":"2","id":"4607","attributes":{},"color":"rgb(52,86,27)","size":12.0},{"source":"28","target":"4","id":"4530","attributes":{},"color":"rgb(52,86,27)","size":1.0},{"source":"16","target":"7","id":"4451","attributes":{},"color":"rgb(157,148,130)","size":24.0},{"source":"37","target":"16","id":"4592","attributes":{},"color":"rgb(52,86,27)","size":1.0},{"source":"17","target":"16","id":"4368","attributes":{},"color":"rgb(104,173,54)","size":1.0},{"source":"12","target":"4","id":"4352","attributes":{},"color":"rgb(157,148,130)","size":5.0},{"source":"20","target":"2","id":"4460","attributes":{},"color":"rgb(52,86,27)","size":3.0},{"source":"31","target":"5","id":"4560","attributes":{},"color":"rgb(52,86,27)","size":36.0},{"source":"36","target":"2","id":"4585","attributes":{},"color":"rgb(52,86,27)","size":11.0},{"source":"14","target":"1","id":"4397","attributes":{},"color":"rgb(210,124,206)","size":11.0},{"source":"19","target":"6","id":"4438","attributes":{},"color":"rgb(210,124,206)","size":7.0},{"source":"32","target":"2","id":"4562","attributes":{},"color":"rgb(52,86,27)","size":23.0},{"source":"37","target":"2","id":"4591","attributes":{},"color":"rgb(52,86,27)","size":4.0},{"source":"26","target":"19","id":"4524","attributes":{},"color":"rgb(105,62,103)","size":1.0},{"source":"22","target":"9","id":"4492","attributes":{},"color":"rgb(127,58,31)","size":9.0},{"source":"25","target":"7","id":"4509","attributes":{},"color":"rgb(105,62,103)","size":159.0},{"source":"6","target":"4","id":"4384","attributes":{},"color":"rgb(157,148,130)","size":51.0},{"source":"14","target":"0","id":"4396","attributes":{},"color":"rgb(210,124,206)","size":1.0},{"source":"18","target":"16","id":"4427","attributes":{},"color":"rgb(157,148,130)","size":1.0},{"source":"41","target":"7","id":"4603","attributes":{},"color":"rgb(105,62,103)","size":1.0},{"source":"5","target":"2","id":"4373","attributes":{},"color":"rgb(104,173,54)","size":11.0},{"source":"15","target":"4","id":"4431","attributes":{},"color":"rgb(157,148,130)","size":1.0},{"source":"21","target":"7","id":"4481","attributes":{},"color":"rgb(105,62,103)","size":54.0},{"source":"34","target":"4","id":"4572","attributes":{},"color":"rgb(52,86,27)","size":2.0},{"source":"35","target":"8","id":"4581","attributes":{},"color":"rgb(0,91,109)","size":2.0},{"source":"1","target":"1","id":"4330","attributes":{},"color":"rgb(210,124,206)","size":1.0},{"source":"12","target":"0","id":"4348","attributes":{},"color":"rgb(210,124,206)","size":26.0},{"source":"26","target":"4","id":"4518","attributes":{},"color":"rgb(52,86,27)","size":2.0},{"source":"26","target":"13","id":"4519","attributes":{},"color":"rgb(127,58,31)","size":1.0},{"source":"14","target":"4","id":"4400","attributes":{},"color":"rgb(157,148,130)","size":2.0},{"source":"41","target":"1","id":"4598","attributes":{},"color":"rgb(105,62,103)","size":5.0},{"source":"23","target":"18","id":"4501","attributes":{},"color":"rgb(105,62,103)","size":1.0},{"source":"0","target":"4","id":"4324","attributes":{},"color":"rgb(157,148,130)","size":105.0},{"source":"22","target":"16","id":"4493","attributes":{},"color":"rgb(52,86,27)","size":1.0},{"source":"14","target":"14","id":"4403","attributes":{},"color":"rgb(210,124,206)","size":81.0},{"source":"23","target":"16","id":"4502","attributes":{},"color":"rgb(52,86,27)","size":1.0},{"source":"32","target":"5","id":"4566","attributes":{},"color":"rgb(52,86,27)","size":3.0},{"source":"17","target":"2","id":"4365","attributes":{},"color":"rgb(104,173,54)","size":1.0},{"source":"16","target":"11","id":"4446","attributes":{},"color":"rgb(104,173,54)","size":1.0},{"source":"7","target":"7","id":"4395","attributes":{},"color":"rgb(210,124,206)","size":14.0},{"source":"10","target":"5","id":"4338","attributes":{},"color":"rgb(104,173,54)","size":1.0},{"source":"34","target":"7","id":"4574","attributes":{},"color":"rgb(105,62,103)","size":5.0},{"source":"20","target":"14","id":"4468","attributes":{},"color":"rgb(105,62,103)","size":204.0},{"source":"48","target":"3","id":"4618","attributes":{},"color":"rgb(52,86,27)","size":1.0},{"source":"16","target":"1","id":"4442","attributes":{},"color":"rgb(157,148,130)","size":18.0},{"source":"11","target":"10","id":"4363","attributes":{},"color":"rgb(104,173,54)","size":62.0},{"source":"15","target":"19","id":"4435","attributes":{},"color":"rgb(210,124,206)","size":1.0},{"source":"19","target":"19","id":"4440","attributes":{},"color":"rgb(210,124,206)","size":3.0},{"source":"33","target":"16","id":"4569","attributes":{},"color":"rgb(52,86,27)","size":1.0},{"source":"40","target":"16","id":"4597","attributes":{},"color":"rgb(52,86,27)","size":1.0},{"source":"35","target":"7","id":"4580","attributes":{},"color":"rgb(105,62,103)","size":4.0},{"source":"20","target":"15","id":"4472","attributes":{},"color":"rgb(105,62,103)","size":12.0},{"source":"15","target":"7","id":"4432","attributes":{},"color":"rgb(210,124,206)","size":6.0},{"source":"38","target":"16","id":"4594","attributes":{},"color":"rgb(52,86,27)","size":1.0},{"source":"28","target":"7","id":"4534","attributes":{},"color":"rgb(105,62,103)","size":2.0},{"source":"0","target":"3","id":"4323","attributes":{},"color":"rgb(157,148,130)","size":1.0},{"source":"48","target":"16","id":"4620","attributes":{},"color":"rgb(52,86,27)","size":1.0},{"source":"14","target":"13","id":"4401","attributes":{},"color":"rgb(232,120,134)","size":5.0},{"source":"34","target":"6","id":"4573","attributes":{},"color":"rgb(105,62,103)","size":4.0},{"source":"53","target":"16","id":"4625","attributes":{},"color":"rgb(52,86,27)","size":3.0},{"source":"42","target":"16","id":"4606","attributes":{},"color":"rgb(52,86,27)","size":1.0},{"source":"8","target":"1","id":"4404","attributes":{},"color":"rgb(105,153,212)","size":10.0},{"source":"26","target":"7","id":"4521","attributes":{},"color":"rgb(105,62,103)","size":41.0},{"source":"52","target":"16","id":"4624","attributes":{},"color":"rgb(52,86,27)","size":1.0},{"source":"16","target":"9","id":"4454","attributes":{},"color":"rgb(179,144,58)","size":10.0},{"source":"18","target":"9","id":"4425","attributes":{},"color":"rgb(232,120,134)","size":6.0},{"source":"29","target":"13","id":"4544","attributes":{},"color":"rgb(127,58,31)","size":37.0},{"source":"23","target":"0","id":"4494","attributes":{},"color":"rgb(105,62,103)","size":2.0},{"source":"34","target":"9","id":"4576","attributes":{},"color":"rgb(127,58,31)","size":4.0},{"source":"12","target":"9","id":"4359","attributes":{},"color":"rgb(232,120,134)","size":19.0},{"source":"28","target":"6","id":"4533","attributes":{},"color":"rgb(105,62,103)","size":2.0},{"source":"13","target":"13","id":"4379","attributes":{},"color":"rgb(255,116,62)","size":5.0},{"source":"16","target":"4","id":"4447","attributes":{},"color":"rgb(104,173,54)","size":3.0},{"source":"22","target":"4","id":"4489","attributes":{},"color":"rgb(52,86,27)","size":3.0},{"source":"3","target":"2","id":"4340","attributes":{},"color":"rgb(104,173,54)","size":168.0},{"source":"26","target":"1","id":"4516","attributes":{},"color":"rgb(105,62,103)","size":77.0},{"source":"6","target":"9","id":"4388","attributes":{},"color":"rgb(232,120,134)","size":1729.0},{"source":"23","target":"3","id":"4496","attributes":{},"color":"rgb(52,86,27)","size":25.0},{"source":"30","target":"8","id":"4554","attributes":{},"color":"rgb(0,91,109)","size":1.0},{"source":"48","target":"8","id":"4619","attributes":{},"color":"rgb(0,91,109)","size":1.0},{"source":"12","target":"5","id":"4353","attributes":{},"color":"rgb(157,148,130)","size":2.0},{"source":"7","target":"6","id":"4394","attributes":{},"color":"rgb(210,124,206)","size":3.0},{"source":"16","target":"0","id":"4441","attributes":{},"color":"rgb(157,148,130)","size":4.0},{"source":"41","target":"8","id":"4604","attributes":{},"color":"rgb(0,91,109)","size":1.0},{"source":"18","target":"1","id":"4418","attributes":{},"color":"rgb(210,124,206)","size":17.0},{"source":"28","target":"5","id":"4531","attributes":{},"color":"rgb(52,86,27)","size":1.0},{"source":"23","target":"9","id":"4500","attributes":{},"color":"rgb(127,58,31)","size":1.0},{"source":"16","target":"14","id":"4452","attributes":{},"color":"rgb(157,148,130)","size":8.0},{"source":"12","target":"14","id":"4357","attributes":{},"color":"rgb(210,124,206)","size":11.0},{"source":"29","target":"2","id":"4539","attributes":{},"color":"rgb(52,86,27)","size":1.0},{"source":"0","target":"0","id":"4320","attributes":{},"color":"rgb(210,124,206)","size":5507.0},{"source":"28","target":"0","id":"4527","attributes":{},"color":"rgb(105,62,103)","size":8.0},{"source":"32","target":"16","id":"4567","attributes":{},"color":"rgb(52,86,27)","size":1.0},{"source":"34","target":"3","id":"4571","attributes":{},"color":"rgb(52,86,27)","size":5.0},{"source":"16","target":"2","id":"4443","attributes":{},"color":"rgb(104,173,54)","size":4.0},{"source":"31","target":"11","id":"4558","attributes":{},"color":"rgb(52,86,27)","size":3.0},{"source":"12","target":"2","id":"4350","attributes":{},"color":"rgb(157,148,130)","size":2.0},{"source":"18","target":"13","id":"4421","attributes":{},"color":"rgb(232,120,134)","size":2.0},{"source":"34","target":"1","id":"4570","attributes":{},"color":"rgb(105,62,103)","size":2.0},{"source":"32","target":"10","id":"4563","attributes":{},"color":"rgb(52,86,27)","size":1.0},{"source":"10","target":"10","id":"4336","attributes":{},"color":"rgb(104,173,54)","size":8.0},{"source":"20","target":"6","id":"4466","attributes":{},"color":"rgb(105,62,103)","size":3.0},{"source":"9","target":"7","id":"4415","attributes":{},"color":"rgb(232,120,134)","size":15.0},{"source":"29","target":"14","id":"4547","attributes":{},"color":"rgb(105,62,103)","size":76.0},{"source":"11","target":"11","id":"4364","attributes":{},"color":"rgb(104,173,54)","size":6.0},{"source":"18","target":"14","id":"4424","attributes":{},"color":"rgb(210,124,206)","size":3.0},{"source":"41","target":"3","id":"4599","attributes":{},"color":"rgb(52,86,27)","size":1.0},{"source":"20","target":"16","id":"4474","attributes":{},"color":"rgb(52,86,27)","size":5.0},{"source":"44","target":"4","id":"4611","attributes":{},"color":"rgb(52,86,27)","size":1.0},{"source":"14","target":"3","id":"4399","attributes":{},"color":"rgb(157,148,130)","size":2.0},{"source":"20","target":"3","id":"4461","attributes":{},"color":"rgb(52,86,27)","size":8.0},{"source":"25","target":"15","id":"4513","attributes":{},"color":"rgb(105,62,103)","size":1.0},{"source":"23","target":"14","id":"4499","attributes":{},"color":"rgb(105,62,103)","size":1.0},{"source":"3","target":"0","id":"4339","attributes":{},"color":"rgb(157,148,130)","size":4.0},{"source":"20","target":"19","id":"4473","attributes":{},"color":"rgb(105,62,103)","size":10.0},{"source":"26","target":"3","id":"4517","attributes":{},"color":"rgb(52,86,27)","size":2.0},{"source":"27","target":"16","id":"4526","attributes":{},"color":"rgb(52,86,27)","size":2.0},{"source":"4","target":"2","id":"4369","attributes":{},"color":"rgb(104,173,54)","size":2.0},{"source":"22","target":"2","id":"4487","attributes":{},"color":"rgb(52,86,27)","size":1.0},{"source":"45","target":"16","id":"4614","attributes":{},"color":"rgb(52,86,27)","size":1.0},{"source":"6","target":"1","id":"4382","attributes":{},"color":"rgb(210,124,206)","size":56.0},{"source":"18","target":"2","id":"4419","attributes":{},"color":"rgb(157,148,130)","size":4.0},{"source":"6","target":"0","id":"4381","attributes":{},"color":"rgb(210,124,206)","size":4375.0},{"source":"26","target":"6","id":"4520","attributes":{},"color":"rgb(105,62,103)","size":2.0},{"source":"21","target":"2","id":"4477","attributes":{},"color":"rgb(52,86,27)","size":3.0},{"source":"4","target":"5","id":"4372","attributes":{},"color":"rgb(104,173,54)","size":63.0},{"source":"15","target":"15","id":"4434","attributes":{},"color":"rgb(210,124,206)","size":428.0},{"source":"20","target":"9","id":"4470","attributes":{},"color":"rgb(127,58,31)","size":2.0},{"source":"8","target":"4","id":"4406","attributes":{},"color":"rgb(52,178,136)","size":1.0},{"source":"49","target":"16","id":"4621","attributes":{},"color":"rgb(52,86,27)","size":2.0},{"source":"41","target":"13","id":"4602","attributes":{},"color":"rgb(127,58,31)","size":1.0},{"source":"18","target":"6","id":"4422","attributes":{},"color":"rgb(210,124,206)","size":14.0},{"source":"13","target":"4","id":"4378","attributes":{},"color":"rgb(179,144,58)","size":4.0},{"source":"20","target":"12","id":"4462","attributes":{},"color":"rgb(105,62,103)","size":19.0},{"source":"12","target":"8","id":"4358","attributes":{},"color":"rgb(105,153,212)","size":6.0},{"source":"7","target":"4","id":"4392","attributes":{},"color":"rgb(157,148,130)","size":1.0},{"source":"31","target":"16","id":"4561","attributes":{},"color":"rgb(52,86,27)","size":1.0},{"source":"9","target":"3","id":"4412","attributes":{},"color":"rgb(179,144,58)","size":1.0},{"source":"0","target":"9","id":"4329","attributes":{},"color":"rgb(232,120,134)","size":2883.0},{"source":"15","target":"14","id":"4433","attributes":{},"color":"rgb(210,124,206)","size":1.0},{"source":"7","target":"1","id":"4390","attributes":{},"color":"rgb(210,124,206)","size":290.0},{"source":"51","target":"16","id":"4623","attributes":{},"color":"rgb(52,86,27)","size":5.0},{"source":"16","target":"5","id":"4448","attributes":{},"color":"rgb(104,173,54)","size":3.0},{"source":"43","target":"4","id":"4608","attributes":{},"color":"rgb(52,86,27)","size":3.0},{"source":"34","target":"15","id":"4577","attributes":{},"color":"rgb(105,62,103)","size":1.0},{"source":"54","target":"16","id":"4626","attributes":{},"color":"rgb(52,86,27)","size":1.0},{"source":"0","target":"8","id":"4328","attributes":{},"color":"rgb(105,153,212)","size":2.0},{"source":"36","target":"14","id":"4588","attributes":{},"color":"rgb(105,62,103)","size":1.0},{"source":"18","target":"18","id":"4426","attributes":{},"color":"rgb(210,124,206)","size":18.0},{"source":"29","target":"5","id":"4543","attributes":{},"color":"rgb(52,86,27)","size":2.0},{"source":"22","target":"1","id":"4486","attributes":{},"color":"rgb(105,62,103)","size":18.0},{"source":"5","target":"4","id":"4375","attributes":{},"color":"rgb(104,173,54)","size":5.0},{"source":"41","target":"5","id":"4601","attributes":{},"color":"rgb(52,86,27)","size":1.0},{"source":"28","target":"1","id":"4528","attributes":{},"color":"rgb(105,62,103)","size":157.0},{"source":"29","target":"16","id":"4550","attributes":{},"color":"rgb(52,86,27)","size":2.0},{"source":"19","target":"13","id":"4437","attributes":{},"color":"rgb(232,120,134)","size":4.0},{"source":"44","target":"16","id":"4612","attributes":{},"color":"rgb(52,86,27)","size":1.0},{"source":"12","target":"15","id":"4360","attributes":{},"color":"rgb(210,124,206)","size":1.0},{"source":"32","target":"4","id":"4565","attributes":{},"color":"rgb(52,86,27)","size":12.0},{"source":"9","target":"6","id":"4414","attributes":{},"color":"rgb(232,120,134)","size":2023.0},{"source":"38","target":"1","id":"4593","attributes":{},"color":"rgb(105,62,103)","size":2.0},{"source":"25","target":"9","id":"4511","attributes":{},"color":"rgb(127,58,31)","size":63.0},{"source":"29","target":"6","id":"4545","attributes":{},"color":"rgb(105,62,103)","size":27.0},{"source":"14","target":"2","id":"4398","attributes":{},"color":"rgb(157,148,130)","size":1.0},{"source":"29","target":"3","id":"4540","attributes":{},"color":"rgb(52,86,27)","size":4.0},{"source":"21","target":"3","id":"4478","attributes":{},"color":"rgb(52,86,27)","size":6.0},{"source":"25","target":"0","id":"4504","attributes":{},"color":"rgb(105,62,103)","size":92.0},{"source":"2","target":"2","id":"4333","attributes":{},"color":"rgb(104,173,54)","size":9.0},{"source":"26","target":"9","id":"4523","attributes":{},"color":"rgb(127,58,31)","size":7.0},{"source":"41","target":"4","id":"4600","attributes":{},"color":"rgb(52,86,27)","size":1.0},{"source":"22","target":"7","id":"4490","attributes":{},"color":"rgb(105,62,103)","size":1.0},{"source":"33","target":"2","id":"4568","attributes":{},"color":"rgb(52,86,27)","size":2.0},{"source":"12","target":"3","id":"4351","attributes":{},"color":"rgb(157,148,130)","size":10.0},{"source":"1","target":"8","id":"4332","attributes":{},"color":"rgb(105,153,212)","size":24.0},{"source":"31","target":"2","id":"4556","attributes":{},"color":"rgb(52,86,27)","size":45.0},{"source":"36","target":"16","id":"4590","attributes":{},"color":"rgb(52,86,27)","size":1.0},{"source":"0","target":"7","id":"4327","attributes":{},"color":"rgb(210,124,206)","size":45.0},{"source":"43","target":"16","id":"4610","attributes":{},"color":"rgb(52,86,27)","size":1.0},{"source":"26","target":"0","id":"4515","attributes":{},"color":"rgb(105,62,103)","size":22.0},{"source":"16","target":"13","id":"4449","attributes":{},"color":"rgb(179,144,58)","size":3.0},{"source":"5","target":"3","id":"4374","attributes":{},"color":"rgb(104,173,54)","size":8.0},{"source":"10","target":"2","id":"4335","attributes":{},"color":"rgb(104,173,54)","size":635.0},{"source":"29","target":"1","id":"4538","attributes":{},"color":"rgb(105,62,103)","size":109.0},{"source":"30","target":"14","id":"4553","attributes":{},"color":"rgb(105,62,103)","size":3.0},{"source":"3","target":"5","id":"4345","attributes":{},"color":"rgb(104,173,54)","size":26.0},{"source":"9","target":"2","id":"4411","attributes":{},"color":"rgb(179,144,58)","size":4.0},{"source":"41","target":"16","id":"4605","attributes":{},"color":"rgb(52,86,27)","size":6.0},{"source":"46","target":"16","id":"4615","attributes":{},"color":"rgb(52,86,27)","size":1.0},{"source":"3","target":"10","id":"4341","attributes":{},"color":"rgb(104,173,54)","size":4.0},{"source":"25","target":"1","id":"4505","attributes":{},"color":"rgb(105,62,103)","size":343.0},{"source":"43","target":"5","id":"4609","attributes":{},"color":"rgb(52,86,27)","size":14.0},{"source":"0","target":"1","id":"4321","attributes":{},"color":"rgb(210,124,206)","size":90.0},{"source":"45","target":"9","id":"4613","attributes":{},"color":"rgb(127,58,31)","size":1.0},{"source":"28","target":"13","id":"4532","attributes":{},"color":"rgb(127,58,31)","size":14.0},{"source":"11","target":"2","id":"4362","attributes":{},"color":"rgb(104,173,54)","size":192.0},{"source":"31","target":"3","id":"4557","attributes":{},"color":"rgb(52,86,27)","size":2.0},{"source":"23","target":"1","id":"4495","attributes":{},"color":"rgb(105,62,103)","size":22.0},{"source":"8","target":"2","id":"4405","attributes":{},"color":"rgb(52,178,136)","size":1.0},{"source":"28","target":"9","id":"4535","attributes":{},"color":"rgb(127,58,31)","size":20.0},{"source":"35","target":"1","id":"4579","attributes":{},"color":"rgb(105,62,103)","size":3.0},{"source":"39","target":"1","id":"4595","attributes":{},"color":"rgb(105,62,103)","size":3.0},{"source":"17","target":"4","id":"4366","attributes":{},"color":"rgb(104,173,54)","size":8.0},{"source":"23","target":"7","id":"4498","attributes":{},"color":"rgb(105,62,103)","size":3.0},{"source":"18","target":"7","id":"4423","attributes":{},"color":"rgb(210,124,206)","size":42.0},{"source":"8","target":"8","id":"4407","attributes":{},"color":"rgb(0,183,218)","size":20.0}]}